fastpluggy_plugin/crud_tools/__init__.py
fastpluggy_plugin/crud_tools/config.py
fastpluggy_plugin/crud_tools/crud_admin.py
fastpluggy_plugin/crud_tools/crud_admin_registry.py
fastpluggy_plugin/crud_tools/crud_link_helper.py
fastpluggy_plugin/crud_tools/menu_tools.py
fastpluggy_plugin/crud_tools/plugin.py
fastpluggy_plugin/crud_tools/schema.py
fastpluggy_plugin/crud_tools/template_tools.py
fastpluggy_plugin/crud_tools/field_types/__init__.py
fastpluggy_plugin/crud_tools/field_types/date_fields.py
fastpluggy_plugin/crud_tools/field_types/dynamic_fields.py
fastpluggy_plugin/crud_tools/field_types/entity_fields.py
fastpluggy_plugin/crud_tools/field_types/enum_fields.py
fastpluggy_plugin/crud_tools/field_types/timedelta_fields.py
fastpluggy_plugin/crud_tools/filters/__init__.py
fastpluggy_plugin/crud_tools/filters/boolean_filter.py
fastpluggy_plugin/crud_tools/filters/datetime_filter.py
fastpluggy_plugin/crud_tools/filters/enum_filter.py
fastpluggy_plugin/crud_tools/filters/filter_factory.py
fastpluggy_plugin/crud_tools/filters/number_filter.py
fastpluggy_plugin/crud_tools/filters/text_filter.py
fastpluggy_plugin/crud_tools/router/__init__.py
fastpluggy_plugin/crud_tools/router/api.py
fastpluggy_plugin/crud_tools/router/crud.py
fastpluggy_plugin/crud_tools/router/crud_admin.py
fastpluggy_plugin/crud_tools/static/css/header_filters.css
fastpluggy_plugin/crud_tools/static/js/dynamic-select.js
fastpluggy_plugin/crud_tools/templates/widgets/data/filter_macros.html.j2
fastpluggy_plugin/crud_tools/templates/widgets/data/filtered_table.html.j2
fastpluggy_plugin/crud_tools/widgets/__init__.py
fastpluggy_plugin/crud_tools/widgets/filtered_table.py
fastpluggy_crud_tools-0.2.13.dist-info/METADATA
fastpluggy_crud_tools-0.2.13.dist-info/WHEEL
fastpluggy_crud_tools-0.2.13.dist-info/entry_points.txt
fastpluggy_crud_tools-0.2.13.dist-info/top_level.txt
fastpluggy_crud_tools-0.2.13.dist-info/RECORD
