Metadata-Version: 2.4
Name: fastpluggy-crud-tools
Version: 0.2.13
Summary: CRUD Tools plugin for Fastpluggy
Author: FastPluggy Team
Requires-Python: >=3.10
Requires-Dist: jinja2
